[
  {
    "stack": "Svelte",
    "percentage": 33.47
  },
  {
    "stack": "Python",
    "percentage": 23.99
  },
  {
    "stack": "TypeScript",
    "percentage": 20.34
  },
  {
    "stack": "HTML",
    "percentage": 7.57
  },
  {
    "stack": "JavaScript",
    "percentage": 5.28
  },
  {
    "stack": "Dart",
    "percentage": 4.85
  },
  {
    "stack": "CSS",
    "percentage": 2.46
  },
  {
    "stack": "CMake",
    "percentage": 0.9
  },
  {
    "stack": "C++",
    "percentage": 0.42
  },
  {
    "stack": "Shell",
    "percentage": 0.26
  },
  {
    "stack": "Swift",
    "percentage": 0.18
  },
  {
    "stack": "Dockerfile",
    "percentage": 0.11
  },
  {
    "stack": "Batchfile",
    "percentage": 0.08
  },
  {
    "stack": "C",
    "percentage": 0.07
  },
  {
    "stack": "Kotlin",
    "percentage": 0.01
  },
  {
    "stack": "Objective-C",
    "percentage": 0.0
  }
]