[
  {
    "stack": "Svelte",
    "percentage": 35.46
  },
  {
    "stack": "TypeScript",
    "percentage": 21.55
  },
  {
    "stack": "Python",
    "percentage": 19.6
  },
  {
    "stack": "HTML",
    "percentage": 8.02
  },
  {
    "stack": "JavaScript",
    "percentage": 5.48
  },
  {
    "stack": "Dart",
    "percentage": 5.14
  },
  {
    "stack": "CSS",
    "percentage": 2.6
  },
  {
    "stack": "CMake",
    "percentage": 0.96
  },
  {
    "stack": "C++",
    "percentage": 0.44
  },
  {
    "stack": "Shell",
    "percentage": 0.28
  },
  {
    "stack": "Swift",
    "percentage": 0.19
  },
  {
    "stack": "Dockerfile",
    "percentage": 0.12
  },
  {
    "stack": "Batchfile",
    "percentage": 0.08
  },
  {
    "stack": "C",
    "percentage": 0.08
  },
  {
    "stack": "Kotlin",
    "percentage": 0.01
  },
  {
    "stack": "Objective-C",
    "percentage": 0.0
  }
]